AUTHORS.rst
CONTRIBUTING.rst
HISTORY.rst
LICENSE
MANIFEST.in
README.rst
setup.cfg
setup.py
docs/Makefile
docs/authors.rst
docs/conf.py
docs/contributing.rst
docs/history.rst
docs/index.rst
docs/installation.rst
docs/make.bat
docs/readme.rst
docs/usage.rst
pysia/__init__.py
pysia/client.py
pysia.egg-info/PKG-INFO
pysia.egg-info/SOURCES.txt
pysia.egg-info/dependency_links.txt
pysia.egg-info/not-zip-safe
pysia.egg-info/requires.txt
pysia.egg-info/top_level.txt
tests/__init__.py
tests/test_pysia.py