Metadata-Version: 1.1
Name: pysia
Version: 0.1.122.1
Summary: Sia bindings for Python 2 & 3
Home-page: https://github.com/jnmclarty/pysia
Author: Jeffrey McLarty
Author-email: jeffrey.mclarty@gmail.com
License: MIT license
Keywords: pysia
Platform: UNKNOWN
Classifier: Development Status :: 3 - Alpha
Classifier: Intended Audience :: Developers
Classifier: License :: OSI Approved :: MIT License
Classifier: Natural Language :: English
Classifier: Programming Language :: Python :: 2
Classifier: Programming Language :: Python :: 2.6
Classifier: Programming Language :: Python :: 2.7
Classifier: Programming Language :: Python :: 3
Classifier: Programming Language :: Python :: 3.3
Classifier: Programming Language :: Python :: 3.4
Classifier: Programming Language :: Python :: 3.5
